bits/__init__.py
pybits-0.0.1.dist-info/METADATA
pybits-0.0.1.dist-info/WHEEL
pybits-0.0.1.dist-info/top_level.txt
pybits-0.0.1.dist-info/RECORD
