Metadata-Version: 2.1
Name: pybits
Version: 0.0.1
Summary: Python bit manipulation
Home-page: UNKNOWN
Author: Zach Morris
Author-email: zacharymorr@outlook.com
License: UNKNOWN
Platform: UNKNOWN
